pyspark_datasources/__init__.py
pyspark_datasources/arrow.py
pyspark_datasources/fake.py
pyspark_datasources/github.py
pyspark_datasources/googlesheets.py
pyspark_datasources/huggingface.py
pyspark_datasources/kaggle.py
pyspark_datasources/lance.py
pyspark_datasources/opensky.py
pyspark_datasources/salesforce.py
pyspark_datasources/simplejson.py
pyspark_datasources/stock.py
pyspark_datasources/weather.py
pyspark_data_sources-0.1.10.dist-info/LICENSE
pyspark_data_sources-0.1.10.dist-info/METADATA
pyspark_data_sources-0.1.10.dist-info/WHEEL
pyspark_data_sources-0.1.10.dist-info/RECORD
