Metadata-Version: 2.3
Name: pyspark-data-sources
Version: 0.1.10
Summary: Custom Spark data sources for reading and writing data in Apache Spark, using the Python Data Source API
License: Apache-2.0
Author: allisonwang-db
Author-email: allison.wang@databricks.com
Requires-Python: >=3.9,<3.13
Classifier: License :: OSI Approved :: Apache Software License
Classifier: Programming Language :: Python :: 3
Classifier: Programming Language :: Python :: 3.9
Classifier: Programming Language :: Python :: 3.10
Classifier: Programming Language :: Python :: 3.11
Classifier: Programming Language :: Python :: 3.12
Provides-Extra: all
Provides-Extra: databricks
Provides-Extra: datasets
Provides-Extra: faker
Provides-Extra: kaggle
Provides-Extra: lance
Provides-Extra: salesforce
Requires-Dist: databricks-sdk (>=0.28.0,<0.29.0) ; extra == "databricks" or extra == "all"
Requires-Dist: datasets (>=2.17.0,<3.0.0) ; extra == "datasets" or extra == "all"
Requires-Dist: faker (>=23.1.0,<24.0.0) ; extra == "faker" or extra == "all"
Requires-Dist: kagglehub[pandas-datasets] (>=0.3.10,<0.4.0) ; extra == "kaggle" or extra == "all"
Requires-Dist: mkdocstrings[python] (>=0.28.0,<0.29.0)
Requires-Dist: pyarrow (>=11.0.0)
Requires-Dist: requests (>=2.31.0,<3.0.0)
Requires-Dist: simple-salesforce (>=1.12.0,<2.0.0) ; extra == "salesforce" or extra == "all"
